params_from_file/__init__.py
params_from_file/generate_tests.py
params_from_file-0.0.2.dist-info/LICENSE
params_from_file-0.0.2.dist-info/METADATA
params_from_file-0.0.2.dist-info/WHEEL
params_from_file-0.0.2.dist-info/top_level.txt
params_from_file-0.0.2.dist-info/RECORD
