Metadata-Version: 2.1
Name: params-from-file
Version: 0.0.2
Summary: Provide data to parameterizezd tests from files
Author: Roland Lukacsi
Author-email: <lukacsiroland01@gmail.com>
License: GNU
Keywords: python,testing,pytest,parametized
Classifier: Development Status :: 1 - Planning
Classifier: Intended Audience :: Developers
Classifier: Programming Language :: Python :: 3
Classifier: Operating System :: Unix
Classifier: Operating System :: MacOS :: MacOS X
Classifier: Operating System :: Microsoft :: Windows
License-File: LICENSE
Requires-Dist: pyyaml
